LICENSE
MANIFEST.in
README.md
README.rst
VERSION
requirements.txt
setup.py
bin/elzzur
elzzur/__init__.py
elzzur/__main__.py
elzzur/board.py
elzzur/languages.py
elzzur/mtdictionary.py
elzzur/snake.py
elzzur/solver.py
elzzur.egg-info/PKG-INFO
elzzur.egg-info/SOURCES.txt
elzzur.egg-info/dependency_links.txt
elzzur.egg-info/requires.txt
elzzur.egg-info/top_level.txt
elzzur/res/board.bad
elzzur/res/board.empty
elzzur/res/board.onerow
elzzur/res/de.board
elzzur/res/de.marisa
elzzur/res/en.board
elzzur/res/en.marisa
elzzur/res/es.board
elzzur/res/es.marisa
elzzur/res/fr.board
elzzur/res/fr.marisa
elzzur/res/it.board
elzzur/res/it.marisa
elzzur/res/nl.board
elzzur/res/nl.marisa
elzzur/res/pt.board
elzzur/res/pt.marisa
licenses/aspell.txt