Metadata-Version: 1.1
Name: elzzur
Version: 0.0.1.0
Summary: elzzur solves a Ruzzle board, listing all the valid words with their scores.
Home-page: https://github.com/pettarin/elzzur
Author: Alberto Pettarin
Author-email: alberto@albertopettarin.it
License: MIT License
Keywords: elzzur,Ruzzle,Ramble,Scrabble,Scarabeo,Paroliere,Snake,board,snake,snakes,solve,solver,MARISA,trie,prefix tree
Platform: UNKNOWN
Classifier: Development Status :: 5 - Production/Stable
Classifier: Environment :: Console
Classifier: Intended Audience :: Developers
Classifier: Intended Audience :: End Users/Desktop
Classifier: License :: OSI Approved :: MIT License
Classifier: Natural Language :: English
Classifier: Operating System :: MacOS :: MacOS X
Classifier: Operating System :: Microsoft :: Windows
Classifier: Operating System :: POSIX :: Linux
Classifier: Programming Language :: Python
Classifier: Programming Language :: Python :: 2
Classifier: Programming Language :: Python :: 2.7
Classifier: Programming Language :: Python :: 3
Classifier: Programming Language :: Python :: 3.4
Classifier: Programming Language :: Python :: 3.5
Classifier: Topic :: Games/Entertainment
Classifier: Topic :: Games/Entertainment :: Board Games
Classifier: Topic :: Games/Entertainment :: Puzzle Games
Classifier: Topic :: Desktop Environment
Classifier: Topic :: Utilities
